OracleDBHandler/__init__.py
OracleDBHandler/oracle_db_handler.py
OracleDBHandler-0.1.0.dist-info/LICENSE
OracleDBHandler-0.1.0.dist-info/METADATA
OracleDBHandler-0.1.0.dist-info/WHEEL
OracleDBHandler-0.1.0.dist-info/top_level.txt
OracleDBHandler-0.1.0.dist-info/RECORD
