Metadata-Version: 2.1
Name: OracleDBHandler
Version: 0.1.0
Summary: A simple OracleDB handler for executing queries with pandas.
Home-page: https://github.com/pvdphong/OracleDBHandler
Author: pvdphong
Author-email: phong.phamvd@homecredit.vn
License: MIT
Classifier: Programming Language :: Python :: 3
Classifier: License :: OSI Approved :: MIT License
Classifier: Operating System :: OS Independent
Requires-Python: >=3.6
License-File: LICENSE
Requires-Dist: pandas
Requires-Dist: oracledb
